fortunecookiepkg/__init__.py
fortunecookiepkg/__main__.py
fortunecookiepkg/fortunecookie.py
fortunecookiepkg-0.1.6.dist-info/LICENSE
fortunecookiepkg-0.1.6.dist-info/METADATA
fortunecookiepkg-0.1.6.dist-info/WHEEL
fortunecookiepkg-0.1.6.dist-info/entry_points.txt
fortunecookiepkg-0.1.6.dist-info/top_level.txt
fortunecookiepkg-0.1.6.dist-info/RECORD
