Metadata-Version: 2.2
Name: fortunecookiepkg
Version: 0.1.6
Summary: A package that shares fortunes, lucky numbers, and themed or personalized messages.
Author-email: Emily Ney <emn8280@nyu.edu>, Nikita Bhaskar <nb3460@nyu.edu>, Ariya Mathrawala <aam9811@nyu.edu>, Oluwapelumi Adesiyan <oea9714@nyu.edu>
License:                     GNU GENERAL PUBLIC LICENSE
Project-URL: Homepage, https://github.com/software-students-spring2025/3-python-package-teamproj3
Project-URL: Repository, https://github.com/software-students-spring2025/3-python-package-teamproj3.git
Project-URL: Bug Tracker, https://github.com/software-students-spring2025/3-python-package-teamproj3/issues
Keywords: python,package,build,tutorial
Classifier: Programming Language :: Python :: 3
Classifier: Intended Audience :: Education
Classifier: License :: OSI Approved :: GNU General Public License v3 (GPLv3)
Classifier: Operating System :: OS Independent
Requires-Python: >=3.7
License-File: LICENSE
Provides-Extra: dev
Requires-Dist: pytest; extra == "dev"
